odoo/addons/stock_picking_show_move_lots/README.rst
odoo/addons/stock_picking_show_move_lots/__init__.py
odoo/addons/stock_picking_show_move_lots/__manifest__.py
odoo/addons/stock_picking_show_move_lots/i18n/ca_ES.po
odoo/addons/stock_picking_show_move_lots/i18n/es.po
odoo/addons/stock_picking_show_move_lots/static/description/icon.png
odoo/addons/stock_picking_show_move_lots/views/stock_picking_views.xml
odoo_addon_stock_picking_show_move_lots-15.0.1.0.0.2.dist-info/METADATA
odoo_addon_stock_picking_show_move_lots-15.0.1.0.0.2.dist-info/WHEEL
odoo_addon_stock_picking_show_move_lots-15.0.1.0.0.2.dist-info/top_level.txt
odoo_addon_stock_picking_show_move_lots-15.0.1.0.0.2.dist-info/RECORD
